pylaplace.py
pylaplace-0.0.5.dist-info/LICENSE
pylaplace-0.0.5.dist-info/METADATA
pylaplace-0.0.5.dist-info/WHEEL
pylaplace-0.0.5.dist-info/top_level.txt
pylaplace-0.0.5.dist-info/RECORD
