Metadata-Version: 2.1
Name: pylaplace
Version: 0.0.5
Summary: Calculate generalized Laplace coefficients
Home-page: https://github.com/SijmeJan/pylaplace
Author: Sijme-Jan Paardekooper
License: UNKNOWN
Keywords: celestial mechanics
Platform: UNKNOWN
Classifier: Development Status :: 3 - Alpha
Classifier: Intended Audience :: Education
Classifier: Topic :: Scientific/Engineering :: Physics
Classifier: License :: OSI Approved :: GNU General Public License (GPL)
Classifier: Programming Language :: Python :: 3
Classifier: Programming Language :: Python :: 3.4
Classifier: Programming Language :: Python :: 3.5
Classifier: Programming Language :: Python :: 3.6
Requires-Dist: scipy
Requires-Dist: numpy
